Products/ZSQLMethods/SQL.py
Products/ZSQLMethods/__init__.py
Products/ZSQLMethods/sqlmethod.gif
Products/ZSQLMethods/Extensions/TestRecord.py
Products/ZSQLMethods/dtml/add.dtml
Products/ZSQLMethods/dtml/edit.dtml
Products/ZSQLMethods/tests/__init__.py
Products/ZSQLMethods/tests/dummy.py
Products/ZSQLMethods/tests/test_SQL.py
Shared/DC/ZRDB/Aqueduct.py
Shared/DC/ZRDB/Connection.py
Shared/DC/ZRDB/DA.py
Shared/DC/ZRDB/RDB.py
Shared/DC/ZRDB/Results.py
Shared/DC/ZRDB/Search.py
Shared/DC/ZRDB/THUNK.py
Shared/DC/ZRDB/TM.py
Shared/DC/ZRDB/__init__.py
Shared/DC/ZRDB/dbi_db.py
Shared/DC/ZRDB/sqlgroup.py
Shared/DC/ZRDB/sqltest.py
Shared/DC/ZRDB/sqlvar.py
Shared/DC/ZRDB/dtml/advanced.dtml
Shared/DC/ZRDB/dtml/connectionAdd.dtml
Shared/DC/ZRDB/dtml/connectionEdit.dtml
Shared/DC/ZRDB/dtml/connectionStatus.dtml
Shared/DC/ZRDB/dtml/connectionTestForm.dtml
Shared/DC/ZRDB/dtml/customDefaultReport.dtml
Shared/DC/ZRDB/dtml/customDefaultZPTReport.dtml
Shared/DC/ZRDB/dtml/searchAdd.dtml
Shared/DC/ZRDB/dtml/test.dtml
Shared/DC/ZRDB/tests/__init__.py
Shared/DC/ZRDB/tests/testArgs.py
Shared/DC/ZRDB/tests/testDA.py
Shared/DC/ZRDB/tests/testResult.py
Shared/DC/ZRDB/tests/testSearch.py
Shared/DC/ZRDB/tests/testTHUNK.py
Shared/DC/ZRDB/tests/testTM.py
Shared/DC/ZRDB/tests/test_caching.py
Shared/DC/ZRDB/tests/test_connection.py
Shared/DC/ZRDB/tests/test_results.py
Shared/DC/ZRDB/tests/test_sqlgroup.py
Shared/DC/ZRDB/tests/test_sqltest.py
Shared/DC/ZRDB/tests/test_sqlvar.py
Shared/DC/ZRDB/www/DBAdapterFolder_icon.gif
Shared/DC/ZRDB/www/DBAdapter_icon.gif
products_zsqlmethods-5.1.dist-info/licenses/LICENSE.rst
products_zsqlmethods-5.1.dist-info/METADATA
products_zsqlmethods-5.1.dist-info/WHEEL
products_zsqlmethods-5.1.dist-info/top_level.txt
products_zsqlmethods-5.1.dist-info/RECORD
