Metadata-Version: 2.4
Name: Products.ZSQLMethods
Version: 5.1
Summary: SQL method support for Zope.
Author-email: Zope Foundation and contributors <zope-dev@zope.dev>
Maintainer-email: Plone Foundation and contributors <zope-dev@zope.dev>
License-Expression: ZPL-2.1
Project-URL: Source, https://github.com/zopefoundation/Products.ZSQLMethods
Project-URL: Issues, https://github.com/zopefoundation/Products.ZSQLMethods/issues
Classifier: Development Status :: 6 - Mature
Classifier: Environment :: Web Environment
Classifier: Framework :: Zope
Classifier: Framework :: Zope :: 5
Classifier: Operating System :: OS Independent
Classifier: Programming Language :: Python :: 3
Classifier: Programming Language :: Python :: 3.10
Classifier: Programming Language :: Python :: 3.11
Classifier: Programming Language :: Python :: 3.12
Classifier: Programming Language :: Python :: 3.13
Classifier: Programming Language :: Python :: 3.14
Classifier: Programming Language :: Python :: Implementation :: CPython
Classifier: Topic :: Database
Classifier: Topic :: Database :: Front-Ends
Requires-Python: >=3.10
License-File: LICENSE.rst
Requires-Dist: Zope>=5
Requires-Dist: Missing
Requires-Dist: Record
Requires-Dist: DocumentTemplate>=3.2.2
Dynamic: license-file
